Metadata-Version: 2.1
Name: ffmpegio-plugin-downloader
Version: 0.1.1
Summary: ffmpegio plugin to download and use the latest FFmpeg release
Home-page: https://python-ffmpegio.github.io/python-ffmpegio-plugin-downloader
License: GPL-2.0 License
Project-URL: Repository, https://github.com/python-ffmpegio/python-ffmpegio-plugin-downloader
Project-URL: Issues, https://github.com/python-ffmpegio/python-ffmpegio-plugin-downloader/issues
Project-URL: Pull Requests, https://github.com/python-ffmpegio/python-ffmpegio-plugin-downloader/pulls
Keywords: multimedia,ffmpeg
Platform: UNKNOWN
Classifier: Development Status :: 4 - Beta
Classifier: License :: OSI Approved :: GNU General Public License v2 (GPLv2)
Classifier: Topic :: Multimedia :: Sound/Audio
Classifier: Topic :: Multimedia :: Sound/Audio :: Capture/Recording
Classifier: Topic :: Multimedia :: Sound/Audio :: Conversion
Classifier: Topic :: Multimedia :: Video
Classifier: Topic :: Multimedia :: Video :: Capture
Classifier: Topic :: Multimedia :: Video :: Conversion
Classifier: Programming Language :: Python :: 3.7
Classifier: Programming Language :: Python :: 3.8
Classifier: Programming Language :: Python :: 3.9
Classifier: Programming Language :: Python :: 3.10
Requires-Python: >=3.7
License-File: LICENSE
Requires-Dist: ffmpeg-downloader
Requires-Dist: pluggy
